{"openapi":"3.1.0","info":{"title":"Shopemaa Platform - QR API","description":"API documentation for Shopemaa Platform QR API","contact":{"name":"Support","email":"support@shopemaa.com"},"version":"1.0.0"},"servers":[{"url":"http://localhost:8281","description":"Local Server"},{"url":"https://stage-api.qrcentraal.com","description":"Stage Server"},{"url":"https://api.qrcentraal.com","description":"Production Server"}],"security":[{"bearerAuth":[]}],"tags":[{"name":"Analytics","description":"Operations related to analytics"},{"name":"OnePage","description":"Operations related to one page"},{"name":"QrCode","description":"Operations related to qr code"},{"name":"BusinessCard","description":"Operations related to business card"},{"name":"Campaign_Public","description":"Operations related to campaign"},{"name":"Project","description":"Operations related to project"},{"name":"CustomSlug","description":"Operations related to custom slug"},{"name":"Content","description":"Operations related to content"},{"name":"Magic","description":"Operations related to magic"},{"name":"BusinessCard_Public","description":"Operations related to business card"},{"name":"Campaign","description":"Operations related to campaign"},{"name":"Project_Public","description":"Operations related to project"},{"name":"UniText","description":"Operations related to unified text"}],"paths":{"/v1/campaigns/{campaignUtm}/subscribe":{"put":{"tags":["Campaign_Public"],"summary":"Subscribe User to Campaign","operationId":"campaignSubscribe","parameters":[{"name":"campaignUtm","in":"path","required":true,"schema":{"type":"string"}}],"requestBody":{"content":{"application/json":{"schema":{"$ref":"#/components/schemas/ReqSubscribe"}}},"required":true},"responses":{"200":{"description":"Subscribe User to Campaign","content":{"application/json":{"schema":{"$ref":"#/components/schemas/APIBooleanResponse"}}}},"400":{"description":"Subscribe User to Campaign","content":{"application/json":{"schema":{"$ref":"#/components/schemas/FailureApiResponse"}}}}},"security":[]}},"/secure/v1/projects/{projectId}":{"get":{"tags":["Project"],"summary":"Get a project by ID","operationId":"projectByIdAndOwner","parameters":[{"name":"projectId","in":"path","required":true,"schema":{"type":"string"}},{"name":"organization_id","in":"query","required":true,"schema":{"type":"string"}}],"responses":{"200":{"description":"Get a project by ID","content":{"application/json":{"schema":{"$ref":"#/components/schemas/ProjectResponse"}}}}},"security":[{"bearerAuth":[]}]},"put":{"tags":["Project"],"summary":"Update a project","operationId":"updateProject","parameters":[{"name":"projectId","in":"path","required":true,"schema":{"type":"string"}}],"requestBody":{"content":{"application/json":{"schema":{"$ref":"#/components/schemas/ReqProjectUpdate"}}},"required":true},"responses":{"200":{"description":"Update a project","content":{"application/json":{"schema":{"$ref":"#/components/schemas/ProjectResponse"}}}},"400":{"description":"Update a project","content":{"application/json":{"schema":{"$ref":"#/components/schemas/FailureApiResponse"}}}}},"security":[{"bearerAuth":[]}]}},"/secure/v1/projects/{projectId}/uni-texts":{"put":{"tags":["UniText"],"summary":"Update uni text data","operationId":"updateUniText","parameters":[{"name":"projectId","in":"path","required":true,"schema":{"type":"string"}}],"requestBody":{"content":{"application/json":{"schema":{"$ref":"#/components/schemas/ReqUniTextCreate"}}},"required":true},"responses":{"200":{"description":"Update uni text data","content":{"application/json":{"schema":{"$ref":"#/components/schemas/AskSuberaResponse"}}}}},"security":[{"bearerAuth":[]}]}},"/secure/v1/projects/{projectId}/seo-metadata":{"put":{"tags":["Project"],"summary":"Update project's SEO metadata","operationId":"updateProjectSeoMetadata","parameters":[{"name":"projectId","in":"path","required":true,"schema":{"type":"string"}}],"requestBody":{"content":{"application/json":{"schema":{"$ref":"#/components/schemas/ReqSeoMetadataUpsert"}}},"required":true},"responses":{"200":{"description":"Update project's SEO metadata","content":{"application/json":{"schema":{"$ref":"#/components/schemas/ProjectResponse"}}}}},"security":[{"bearerAuth":[]}]}},"/secure/v1/projects/{projectId}/qr-codes/configs":{"put":{"tags":["QrCode"],"summary":"Update QR Code config","operationId":"qrCodeConfigUpdate","parameters":[{"name":"projectId","in":"path","required":true,"schema":{"type":"string"}}],"requestBody":{"content":{"application/json":{"schema":{"$ref":"#/components/schemas/ReqQrCodeConfigUpdate"}}},"required":true},"responses":{"200":{"description":"Update QR Code config","content":{"application/json":{"schema":{"$ref":"#/components/schemas/QrCodeConfigResponse"}}}}},"security":[{"bearerAuth":[]}]}},"/secure/v1/projects/{projectId}/one-pages":{"put":{"tags":["OnePage"],"summary":"Update a one page","operationId":"upsertOnePage","parameters":[{"name":"projectId","in":"path","required":true,"schema":{"type":"string"}}],"requestBody":{"content":{"application/json":{"schema":{"$ref":"#/components/schemas/ReqOnePageUpsert"}}},"required":true},"responses":{"200":{"description":"Update a one page","content":{"application/json":{"schema":{"$ref":"#/components/schemas/OnePageResponse"}}}}},"security":[{"bearerAuth":[]}]}},"/secure/v1/projects/{projectId}/content-cards":{"put":{"tags":["Content"],"operationId":"createContentCard","parameters":[{"name":"projectId","in":"path","required":true,"schema":{"type":"string"}},{"name":"req","in":"query","required":true,"schema":{"$ref":"#/components/schemas/ReqContentCardUpsert"}}],"responses":{"200":{"description":"OK","content":{"*/*":{"schema":{"$ref":"#/components/schemas/ContentCardResponse"}}}}},"security":[{"bearerAuth":[]}]}},"/secure/v1/projects/{projectId}/campaigns":{"put":{"tags":["Campaign"],"summary":"Create a campaign","operationId":"campaignUpsert","parameters":[{"name":"projectId","in":"path","required":true,"schema":{"type":"string"}}],"requestBody":{"content":{"application/json":{"schema":{"$ref":"#/components/schemas/ReqCampaignCreate"}}},"required":true},"responses":{"200":{"description":"Creates a campaign","content":{"application/json":{"schema":{"$ref":"#/components/schemas/CampaignSuccessResponse"}}}},"400":{"description":"Creates a campaign","content":{"application/json":{"schema":{"$ref":"#/components/schemas/FailureApiResponse"}}}}},"security":[{"bearerAuth":[]}]}},"/secure/v1/projects/{projectId}/campaigns/subscriber-configs":{"put":{"tags":["Campaign"],"summary":"Setup campaign subscriber config","operationId":"campaignSubscriberConfig","parameters":[{"name":"projectId","in":"path","required":true,"schema":{"type":"string"}}],"requestBody":{"content":{"application/json":{"schema":{"$ref":"#/components/schemas/ReqCampaignSubscriberConfig"}}},"required":true},"responses":{"200":{"description":"Setup campaign subscriber config","content":{"application/json":{"schema":{"$ref":"#/components/schemas/CampaignSuccessResponse"}}}},"400":{"description":"Setup campaign subscriber config","content":{"application/json":{"schema":{"$ref":"#/components/schemas/FailureApiResponse"}}}}},"security":[{"bearerAuth":[]}]}},"/secure/v1/projects/{projectId}/campaigns/coupon-configs":{"put":{"tags":["Campaign"],"summary":"Setup campaign coupon config","operationId":"campaignCouponConfig","parameters":[{"name":"projectId","in":"path","required":true,"schema":{"type":"string"}}],"requestBody":{"content":{"application/json":{"schema":{"$ref":"#/components/schemas/ReqCampaignCouponConfig"}}},"required":true},"responses":{"200":{"description":"Setup campaign coupon config","content":{"application/json":{"schema":{"$ref":"#/components/schemas/CampaignSuccessResponse"}}}},"400":{"description":"Setup campaign coupon config","content":{"application/json":{"schema":{"$ref":"#/components/schemas/FailureApiResponse"}}}}},"security":[{"bearerAuth":[]}]}},"/secure/v1/projects/{projectId}/business-cards":{"put":{"tags":["BusinessCard"],"summary":"Update a business card","operationId":"upsertBusinessCard","parameters":[{"name":"projectId","in":"path","required":true,"schema":{"type":"string"}}],"requestBody":{"content":{"application/json":{"schema":{"$ref":"#/components/schemas/ReqBusinessCardUpsert"}}},"required":true},"responses":{"200":{"description":"Update a business card","content":{"application/json":{"schema":{"$ref":"#/components/schemas/BusinessCardResponse"}}}},"400":{"description":"Creates a business card","content":{"application/json":{"schema":{"$ref":"#/components/schemas/FailureApiResponse"}}}}},"security":[{"bearerAuth":[]}]}},"/secure/v1/custom-slugs/{projectId}/claim":{"put":{"tags":["CustomSlug"],"summary":"Claim a custom slug","operationId":"customSlugClaim","parameters":[{"name":"projectId","in":"path","required":true,"schema":{"type":"string"}}],"requestBody":{"content":{"application/json":{"schema":{"$ref":"#/components/schemas/ReqClaimCustomSlug"}}},"required":true},"responses":{"200":{"description":"Claim a custom slug","content":{"application/json":{"schema":{"$ref":"#/components/schemas/APIBooleanResponse"}}}}},"security":[{"bearerAuth":[]}]}},"/v1/campaigns/{campaignUtm}/subscriber-email-verify":{"post":{"tags":["Campaign_Public"],"summary":"Subscribed User email verification","operationId":"campaignSubscriberEmailVerify","parameters":[{"name":"campaignUtm","in":"path","required":true,"schema":{"type":"string"}}],"requestBody":{"content":{"application/json":{"schema":{"$ref":"#/components/schemas/ReqSubscribeEmailVerify"}}},"required":true},"responses":{"200":{"description":"Subscribed User email verification","content":{"application/json":{"schema":{"$ref":"#/components/schemas/APIBooleanResponse"}}}},"400":{"description":"Subscribed User email verification","content":{"application/json":{"schema":{"$ref":"#/components/schemas/FailureApiResponse"}}}}},"security":[]}},"/secure/v1/projects":{"get":{"tags":["Project"],"summary":"List projects by organization","operationId":"listProjects","parameters":[{"name":"query","in":"query","required":false,"schema":{"type":"string","default":""}},{"name":"currentPage","in":"query","required":false,"schema":{"type":"integer","format":"int32","default":0,"maximum":1000}},{"name":"perPage","in":"query","required":false,"schema":{"type":"integer","format":"int32","default":10,"maximum":25}},{"name":"organization_id","in":"query","required":true,"schema":{"type":"string"}}],"responses":{"200":{"description":"List projects by organization","content":{"application/json":{"schema":{"$ref":"#/components/schemas/ProjectListResponse"}}}}},"security":[{"bearerAuth":[]}]},"post":{"tags":["Project"],"summary":"Create a project","operationId":"createProject","requestBody":{"content":{"application/json":{"schema":{"$ref":"#/components/schemas/ReqProjectCreate"}}},"required":true},"responses":{"201":{"description":"Create a project","content":{"application/json":{"schema":{"$ref":"#/components/schemas/ProjectResponse"}}}},"400":{"description":"Create a project","content":{"application/json":{"schema":{"$ref":"#/components/schemas/FailureApiResponse"}}}}},"security":[{"bearerAuth":[]}]}},"/secure/v1/magic":{"post":{"tags":["Magic"],"summary":"Ask Subera anything","operationId":"magic","parameters":[{"name":"organizationId","in":"query","required":true,"schema":{"type":"string","minLength":1}}],"requestBody":{"content":{"application/json":{"schema":{"$ref":"#/components/schemas/ReqAskSubera"}}},"required":true},"responses":{"200":{"description":"Ask Subera anything","content":{"application/json":{"schema":{"$ref":"#/components/schemas/AskSuberaResponse"}}}}},"security":[{"bearerAuth":[]}]}},"/v1/projects/{projectSlug}":{"get":{"tags":["Project_Public"],"summary":"Get project by slug","operationId":"projectBySlug","parameters":[{"name":"projectSlug","in":"path","required":true,"schema":{"type":"string"}}],"responses":{"200":{"description":"Get project by slug","content":{"application/json":{"schema":{"$ref":"#/components/schemas/ProjectResponse"}}}}},"security":[]}},"/v1/business-cards/{businessCardId}/download":{"get":{"tags":["BusinessCard_Public"],"summary":"Download business card by ID","operationId":"downloadBusinessCard","parameters":[{"name":"businessCardId","in":"path","required":true,"schema":{"type":"string"}}],"responses":{"200":{"description":"Download business card by ID","content":{"application/octet-stream":{}}}},"security":[]}},"/secure/v1/projects/{projectId}/qr-codes/generate":{"get":{"tags":["QrCode"],"summary":"Generates a QR Code","operationId":"generateQr","parameters":[{"name":"qrOutputFormat","in":"query","required":false,"schema":{"type":"string","default":"PNG","enum":["PNG","SVG"]}},{"name":"projectId","in":"path","required":true,"schema":{"type":"string"}}],"responses":{"200":{"description":"Generates a QR Code","content":{"application/octet-stream":{}}}},"security":[{"bearerAuth":[]}]}},"/secure/v1/projects/{projectId}/qr-codes/generate-pdf":{"get":{"tags":["QrCode"],"summary":"Generates a QR Code as PDF","operationId":"generateQrAsPdf","parameters":[{"name":"projectId","in":"path","required":true,"schema":{"type":"string"}},{"name":"qrSize","in":"query","required":false,"schema":{"type":"integer","format":"int32","default":150,"minimum":50}}],"responses":{"200":{"description":"Generates a QR Code as PDF","content":{"application/pdf":{}}}},"security":[{"bearerAuth":[]}]}},"/secure/v1/projects/{projectId}/campaigns/subscribers":{"get":{"tags":["Campaign"],"summary":"List or Search subscribed users by Campaign","operationId":"listCampaignSubscribedUsers","parameters":[{"name":"projectId","in":"path","required":true,"schema":{"type":"string"}},{"name":"query","in":"query","required":false,"schema":{"type":"string"}},{"name":"limit","in":"query","required":true,"schema":{"type":"integer","format":"int32"}},{"name":"current_page","in":"query","required":true,"schema":{"type":"integer","format":"int32"}}],"responses":{"200":{"description":"List or Search subscribed users by Campaign","content":{"application/json":{"schema":{"$ref":"#/components/schemas/CampaignSubscriberListResponse"}}}}},"security":[{"bearerAuth":[]}]}},"/secure/v1/projects/content-cards/{contentCardId}":{"get":{"tags":["Content"],"operationId":"getContentCardById","parameters":[{"name":"contentCardId","in":"path","required":true,"schema":{"type":"string"}}],"responses":{"200":{"description":"OK","content":{"*/*":{"schema":{"type":"string","format":"byte"}}}}},"security":[{"bearerAuth":[]}]}},"/secure/v1/custom-slugs/check":{"get":{"tags":["CustomSlug"],"summary":"Check if a custom slug is available","operationId":"customSlugCheck","parameters":[{"name":"slug","in":"query","required":true,"schema":{"type":"string","minLength":1}}],"responses":{"200":{"description":"Check if a custom slug is available","content":{"application/json":{"schema":{"$ref":"#/components/schemas/APIBooleanResponse"}}}}},"security":[{"bearerAuth":[]}]}},"/secure/v1/analytics/{projectId}/stats":{"get":{"tags":["Analytics"],"summary":"Get project analytics stats","operationId":"analyticsTraffic","parameters":[{"name":"projectId","in":"path","required":true,"schema":{"type":"string"}},{"name":"fromDate","in":"query","required":false,"schema":{"type":"string","pattern":"^(|\\d{4}-\\d{2}-\\d{2})$"}},{"name":"toDate","in":"query","required":false,"schema":{"type":"string","pattern":"^(|\\d{4}-\\d{2}-\\d{2})$"}}],"responses":{"200":{"description":"Get project analytics stats","content":{"application/json":{"schema":{"$ref":"#/components/schemas/AnalyticsSuccessResponse"}}}}},"security":[{"bearerAuth":[]}]}}},"components":{"schemas":{"ReqSubscribe":{"type":"object","properties":{"utm_qrcu":{"type":"string","minLength":1},"first_name":{"type":"string","minLength":1},"last_name":{"type":"string","minLength":1},"email":{"type":"string"},"phone":{"type":"string"}}},"APIBooleanResponse":{"type":"object","properties":{"data":{"type":"boolean"}}},"ErrorResponse":{"type":"object","properties":{"errors":{"type":"object","additionalProperties":{"type":"array","items":{"type":"string"}}},"error_code":{"type":"string"},"error_message":{"type":"string"}}},"FailureApiResponse":{"type":"object","properties":{"data":{"type":"object","writeOnly":true},"error":{"$ref":"#/components/schemas/ErrorResponse"}}},"ReqProjectUpdate":{"type":"object","properties":{"name":{"type":"string","minLength":1},"description":{"type":"string"},"organization_id":{"type":"string","minLength":1}}},"AddressApiModel":{"type":"object","properties":{"id":{"type":"string"},"street":{"type":"string"},"city":{"type":"string"},"state":{"type":"string"},"country":{"$ref":"#/components/schemas/CountryApiModel"},"street_optional":{"type":"string"},"postal_code":{"type":"string"}}},"BusinessCardApiModel":{"type":"object","properties":{"id":{"type":"string"},"email":{"type":"string"},"phone":{"type":"string"},"website":{"type":"string"},"department":{"type":"string"},"address":{"$ref":"#/components/schemas/AddressApiModel"},"first_name":{"type":"string"},"last_name":{"type":"string"},"job_title":{"type":"string"},"current_company":{"type":"string"},"company_logo_path":{"type":"string"},"company_tagline":{"type":"string"},"selected_template":{"type":"string"},"primary_color":{"type":"string"},"secondary_color":{"type":"string"},"social_links":{"type":"array","items":{"$ref":"#/components/schemas/SocialLink"}},"public_url_path":{"type":"string"}}},"CampaignApiModel":{"type":"object","properties":{"id":{"type":"string"},"utm_campaign":{"type":"string"},"title":{"type":"string"},"slug":{"type":"string"},"subtitle":{"type":"string"},"description":{"type":"string"},"banner_image_path":{"type":"string"},"additional_images":{"type":"array","items":{"type":"string"},"uniqueItems":true},"campaign_action":{"type":"string","enum":["SUBSCRIBE","PRODUCT_LIST","SHOW_SPIN","GENERATE_COUPON","SELL_TICKET","APPOINTMENT","NONE","WHATSAPP_CONTACT"]},"campaign_action_btn_label":{"type":"string"},"post_action_event":{"type":"string","enum":["SUBSCRIBE","PRODUCT_LIST","SHOW_SPIN","GENERATE_COUPON","SELL_TICKET","APPOINTMENT","NONE","WHATSAPP_CONTACT"]},"post_action_event_btn_label":{"type":"string"},"campaign_type":{"type":"string","enum":["GENERIC","REAL_ESTATE","PHYSICAL_PRODUCT","DIGITAL_PRODUCT","MENU_ITEM"]},"status":{"type":"string","enum":["ACTIVE","INACTIVE"]},"created_at":{"type":"string"},"start_date":{"type":"string","format":"date"},"end_date":{"type":"string","format":"date"},"start_time":{"type":"string","example":"14:30:00+01:00"},"end_time":{"type":"string","example":"14:30:00+01:00"},"subscriber_config":{"$ref":"#/components/schemas/CampaignSubscribeConfigApiModel"},"coupon_config":{"$ref":"#/components/schemas/CampaignCouponConfigApiModel"}}},"CampaignCouponConfigApiModel":{"type":"object","properties":{"discount_type":{"type":"string","enum":["FIXED","PERCENTAGE"]},"discount_amount":{"type":"integer","format":"int32"},"valid_from":{"type":"string","format":"date"},"valid_to":{"type":"string","format":"date"},"max_usage":{"type":"integer","format":"int32"}}},"CampaignSubscribeConfigApiModel":{"type":"object","properties":{"is_phone_required":{"type":"boolean"},"is_email_required":{"type":"boolean"},"is_phone_verification_required":{"type":"boolean"},"is_email_verification_required":{"type":"boolean"}}},"CountryApiModel":{"type":"object","properties":{"id":{"type":"string"},"code":{"type":"string"},"name":{"type":"string"}}},"OnePageApiModel":{"type":"object","properties":{"id":{"type":"string"},"blocks":{"type":"string"}}},"ProjectApiDto":{"type":"object","properties":{"id":{"type":"string"},"name":{"type":"string"},"description":{"type":"string"},"type":{"type":"string","enum":["BusinessCard","ContentCard","RestaurantMenu","Campaign","UniText","OnePage"]},"project_slug":{"type":"string"},"qr_code_config":{"$ref":"#/components/schemas/QrCodeConfigApiModel"},"business_card":{"$ref":"#/components/schemas/BusinessCardApiModel"},"uni_text":{"$ref":"#/components/schemas/UniTextApiDto"},"campaign":{"$ref":"#/components/schemas/CampaignApiModel"},"one_page":{"$ref":"#/components/schemas/OnePageApiModel"},"seo_metadata":{"$ref":"#/components/schemas/SeoMetadataApiDto"},"created_at":{"type":"string","format":"date-time"}}},"ProjectResponse":{"type":"object","properties":{"data":{"$ref":"#/components/schemas/ProjectApiDto"}}},"QrCodeConfigApiModel":{"type":"object","properties":{"background_color":{"type":"string"},"fill_color":{"type":"string"},"logo_path":{"type":"string"},"qr_pattern":{"type":"string","enum":["TRIANGLE","HEART","DIAMOND","HEXAGON","HOUSE","STAR","CROSS"]},"qr_shape":{"type":"string","enum":["SQUARE","CIRCLE"]},"qr_header_text":{"type":"string"},"qr_footer_text":{"type":"string"},"qr_size":{"type":"integer","format":"int32"},"qr_image_path":{"type":"string"}}},"SeoMetadataApiDto":{"type":"object","properties":{"title":{"type":"string"},"description":{"type":"string"},"banner_path":{"type":"string"},"url":{"type":"string"},"favicon_path":{"type":"string"}}},"SocialLink":{"type":"object","properties":{"type":{"type":"string","minLength":1},"url":{"type":"string","minLength":1}}},"UniTextApiDto":{"type":"object","properties":{"id":{"type":"string"},"data":{"type":"string"},"extra_data":{"type":"string"},"uni_text_type":{"type":"string","enum":["PLAIN_TEXT","URL","PHONE_NUMBER","EMAIL","WHATSAPP","JSON","PORTFOLIO_PAGE"]}}},"ReqUniTextCreate":{"type":"object","properties":{"data":{"type":"string","minLength":1},"extra_data":{"type":"string"},"uni_text_type":{"type":"string","enum":["PLAIN_TEXT","URL","PHONE_NUMBER","EMAIL","WHATSAPP","JSON","PORTFOLIO_PAGE"]}},"required":["uni_text_type"]},"AskSuberaResponse":{"type":"object","properties":{"data":{"type":"string"}}},"ReqSeoMetadataUpsert":{"type":"object","properties":{"title":{"type":"string"},"description":{"type":"string"},"banner_path":{"type":"string"},"url":{"type":"string"},"favicon_path":{"type":"string"}}},"ReqQrCodeConfigUpdate":{"type":"object","properties":{"background_color":{"type":"string"},"fill_color":{"type":"string"},"logo_path":{"type":"string"},"qr_pattern":{"type":"string","enum":["TRIANGLE","HEART","DIAMOND","HEXAGON","HOUSE","STAR","CROSS"]},"qr_shape":{"type":"string","enum":["SQUARE","CIRCLE"]},"qr_header_text":{"type":"string","maxLength":20,"minLength":0},"qr_footer_text":{"type":"string","maxLength":20,"minLength":0},"qr_size":{"type":"integer","format":"int32","minimum":150}}},"QrCodeConfigResponse":{"type":"object","properties":{"data":{"$ref":"#/components/schemas/QrCodeConfigApiModel"}}},"ReqOnePageUpsert":{"type":"object","properties":{"id":{"type":"string"},"blocks":{"type":"string","minLength":1}}},"OnePageResponse":{"type":"object","properties":{"data":{"$ref":"#/components/schemas/OnePageApiModel"}}},"ReqContentCardUpsert":{"type":"object","properties":{"contentFile":{"type":"string","format":"binary"},"title":{"type":"string"},"passwordProtected":{"type":"boolean"},"password":{"type":"string"}}},"ContentCardApiDto":{"type":"object","properties":{"id":{"type":"string"},"title":{"type":"string"},"password_protected":{"type":"boolean"},"content_type":{"type":"string"},"content_path":{"type":"string"},"content_url":{"type":"string"}}},"ContentCardResponse":{"type":"object","properties":{"data":{"$ref":"#/components/schemas/ContentCardApiDto"}}},"ReqCampaignCreate":{"type":"object","properties":{"title":{"type":"string","minLength":1},"subtitle":{"type":"string"},"description":{"type":"string"},"banner_image_path":{"type":"string"},"additional_images":{"type":"array","items":{"type":"string"},"uniqueItems":true},"campaign_type":{"type":"string","enum":["GENERIC","REAL_ESTATE","PHYSICAL_PRODUCT","DIGITAL_PRODUCT","MENU_ITEM"]},"campaign_status":{"type":"string","enum":["ACTIVE","INACTIVE"]},"action_event":{"type":"string","enum":["SUBSCRIBE","PRODUCT_LIST","SHOW_SPIN","GENERATE_COUPON","SELL_TICKET","APPOINTMENT","NONE","WHATSAPP_CONTACT"]},"action_event_btn_label":{"type":"string"},"post_action_event":{"type":"string","enum":["SUBSCRIBE","PRODUCT_LIST","SHOW_SPIN","GENERATE_COUPON","SELL_TICKET","APPOINTMENT","NONE","WHATSAPP_CONTACT"]},"post_action_event_btn_label":{"type":"string"},"start_date":{"type":"string","format":"date"},"end_date":{"type":"string","format":"date"},"start_time":{"type":"string","example":"14:30:00+01:00"},"end_time":{"type":"string","example":"14:30:00+01:00"}}},"CampaignSuccessResponse":{"type":"object","properties":{"data":{"$ref":"#/components/schemas/CampaignApiModel"}}},"ReqCampaignSubscriberConfig":{"type":"object","properties":{"is_phone_required":{"type":"boolean"},"is_email_required":{"type":"boolean"},"is_phone_verification_required":{"type":"boolean"},"is_email_verification_required":{"type":"boolean"}}},"ReqCampaignCouponConfig":{"type":"object","properties":{"discount_type":{"type":"string","enum":["FIXED","PERCENTAGE"]},"discount_amount":{"type":"integer","format":"int32"},"valid_from":{"type":"string","format":"date"},"valid_to":{"type":"string","format":"date"},"max_usage":{"type":"integer","format":"int32"}}},"ReqBusinessCardUpsert":{"type":"object","properties":{"email":{"type":"string","minLength":1},"phone":{"type":"string","minLength":1},"website":{"type":"string","minLength":1},"department":{"type":"string"},"first_name":{"type":"string","minLength":1},"last_name":{"type":"string","minLength":1},"job_title":{"type":"string","minLength":1},"current_company":{"type":"string","minLength":1},"company_logo_path":{"type":"string","minLength":1},"company_tagline":{"type":"string"},"primary_color":{"type":"string"},"secondary_color":{"type":"string"},"social_links":{"type":"array","items":{"$ref":"#/components/schemas/SocialLink"}},"selected_template":{"type":"string"},"address":{"$ref":"#/components/schemas/ReqCreateBusinessCard_Address"}},"required":["address"]},"ReqCreateBusinessCard_Address":{"type":"object","properties":{"street":{"type":"string","minLength":1},"city":{"type":"string","minLength":1},"state":{"type":"string"},"street_optional":{"type":"string"},"postal_code":{"type":"string","minLength":1},"country_id":{"type":"string","minLength":1}}},"BusinessCardResponse":{"type":"object","properties":{"data":{"$ref":"#/components/schemas/BusinessCardApiModel"}}},"ReqClaimCustomSlug":{"type":"object","properties":{"slug":{"type":"string"},"organization_id":{"type":"string"}}},"ReqSubscribeEmailVerify":{"type":"object","properties":{"email":{"type":"string","minLength":1},"token":{"type":"string","minLength":1}}},"ReqProjectCreate":{"type":"object","properties":{"name":{"type":"string","minLength":1},"description":{"type":"string"},"type":{"type":"string","enum":["BusinessCard","ContentCard","RestaurantMenu","Campaign","UniText","OnePage"]},"organization_id":{"type":"string","minLength":1},"foreign_reference_id":{"type":"string"}},"required":["type"]},"ReqAskSubera":{"type":"object","properties":{"query":{"type":"string","minLength":1},"prev_content":{"type":"string"}}},"PaginatedResultProjectApiDto":{"type":"object","properties":{"total_items":{"type":"integer","format":"int64"},"total_pages":{"type":"integer","format":"int32"},"current_page":{"type":"integer","format":"int32"},"limit":{"type":"integer","format":"int32"},"items":{"type":"array","items":{"$ref":"#/components/schemas/ProjectApiDto"}}}},"ProjectListResponse":{"type":"object","properties":{"data":{"$ref":"#/components/schemas/PaginatedResultProjectApiDto"}}},"CampaignSubscribedUserApiModel":{"type":"object","properties":{"id":{"type":"string"},"first_name":{"type":"string"},"last_name":{"type":"string"},"email":{"type":"string"},"phone":{"type":"string"},"is_email_verified":{"type":"boolean"},"is_phone_verified":{"type":"boolean"},"subscribed_at":{"type":"string","format":"date-time"}}},"CampaignSubscriberListResponse":{"type":"object","properties":{"data":{"type":"array","items":{"$ref":"#/components/schemas/CampaignSubscribedUserApiModel"}}}},"AnalyticsSuccessResponse":{"type":"object","properties":{"data":{"$ref":"#/components/schemas/RespAnalytics"}}},"DeviceBreakdown":{"type":"object","properties":{"os":{"type":"string"},"browser":{"type":"string"},"visits":{"type":"integer","format":"int32"},"visits_per_user":{"type":"number","format":"double"}}},"GeoBreakdown":{"type":"object","properties":{"country":{"type":"string"},"city":{"type":"string"},"visits":{"type":"integer","format":"int32"},"visits_per_user":{"type":"number","format":"double"}}},"RespAnalytics":{"type":"object","properties":{"total_visits":{"type":"integer","format":"int32"},"unique_visits":{"type":"integer","format":"int32"},"visit_per_user":{"type":"number","format":"double"},"bounce_rate":{"type":"number","format":"double"},"avg_session_duration":{"type":"number","format":"double"},"geo_breakdowns":{"type":"array","items":{"$ref":"#/components/schemas/GeoBreakdown"}},"device_breakdowns":{"type":"array","items":{"$ref":"#/components/schemas/DeviceBreakdown"}},"timeseries":{"type":"array","items":{"$ref":"#/components/schemas/TimeseriesPoint"}}}},"TimeseriesPoint":{"type":"object","properties":{"date":{"type":"string"},"total_scans":{"type":"integer","format":"int32"},"unique_scans":{"type":"integer","format":"int32"}}}},"securitySchemes":{"bearerAuth":{"type":"http","scheme":"bearer","bearerFormat":"JWT"}}}}